caller/__init__.py
caller/apps.py
caller/utils.py
caller/version.py
caller/templatetags/__init__.py
caller/templatetags/caller_tags.py
example/__init__.py
example/admin.py
example/api.py
example/models.py
example/settings.py
example/urls.py
example/views.py
example/wsgi.py
example/migrations/0001_initial.py
example/migrations/__init__.py
tests/__init__.py
tests/settings.py
tests/test_tags.py
tests/utils.py
django_rest_caller-0.2.2.dist-info/AUTHORS
django_rest_caller-0.2.2.dist-info/COPYING
django_rest_caller-0.2.2.dist-info/METADATA
django_rest_caller-0.2.2.dist-info/WHEEL
django_rest_caller-0.2.2.dist-info/top_level.txt
django_rest_caller-0.2.2.dist-info/RECORD
