Metadata-Version: 2.1
Name: django-rest-caller
Version: 0.2.2
Summary: templatetag to call an urlconf and store its payload into the template context
Home-page: https://bitbucket.org/rsalmaso/django-rest-caller
Author: Raffaele Salmaso
Author-email: raffele@salmaso.org
License: MIT
Platform: UNKNOWN
Classifier: Framework :: Django
Classifier: Framework :: Django :: 1.11
Classifier: Framework :: Django :: 2.0
Classifier: Intended Audience :: Developers
Classifier: License :: OSI Approved :: MIT License
Classifier: Programming Language :: Python
Classifier: Programming Language :: Python :: 3
Classifier: Programming Language :: Python :: 3.4
Classifier: Programming Language :: Python :: 3.5
Classifier: Programming Language :: Python :: 3.6
Requires-Python: >=3.4
Requires-Dist: django
